mloptimizer/VERSION
mloptimizer/__init__.py
mloptimizer/__main__.py
mloptimizer/application/__init__.py
mloptimizer/application/hyperparameter_space_service.py
mloptimizer/application/optimizer_service.py
mloptimizer/application/utils.py
mloptimizer/application/reporting/__init__.py
mloptimizer/application/reporting/plots.py
mloptimizer/domain/__init__.py
mloptimizer/domain/evaluation/__init__.py
mloptimizer/domain/evaluation/eval_utils.py
mloptimizer/domain/evaluation/evaluator.py
mloptimizer/domain/evaluation/model_evaluation.py
mloptimizer/domain/hyperspace/__init__.py
mloptimizer/domain/hyperspace/hyperparam.py
mloptimizer/domain/hyperspace/hyperspace.py
mloptimizer/domain/model/__init__.py
mloptimizer/domain/model/alg_wrapper.py
mloptimizer/domain/optimization/__init__.py
mloptimizer/domain/optimization/genetic_algorithm.py
mloptimizer/domain/optimization/keras_classifier_optimizer.py
mloptimizer/domain/optimization/optimizer.py
mloptimizer/domain/population/__init__.py
mloptimizer/domain/population/individual.py
mloptimizer/domain/population/population.py
mloptimizer/infrastructure/__init__.py
mloptimizer/infrastructure/config/hyperspace/default_hyperparameter_spaces.json
mloptimizer/infrastructure/config/hyperspace/catboost/CatBoostClassifier_default_HyperparamSpace.json
mloptimizer/infrastructure/config/hyperspace/catboost/CatBoostRegressor_default_HyperparamSpace.json
mloptimizer/infrastructure/config/hyperspace/lightgbm/LGBMClassifier_default_HyperparamSpace.json
mloptimizer/infrastructure/config/hyperspace/lightgbm/LGBMRegressor_default_HyperparamSpace.json
mloptimizer/infrastructure/config/hyperspace/sklearn/AdaBoostClassifier_default_HyperparamSpace.json
mloptimizer/infrastructure/config/hyperspace/sklearn/AdaBoostRegressor_default_HyperparamSpace.json
mloptimizer/infrastructure/config/hyperspace/sklearn/DecisionTreeClassifier_default_HyperparamSpace.json
mloptimizer-0.9.4.dist-info/licenses/LICENSE
mloptimizer-0.9.4.dist-info/METADATA
mloptimizer-0.9.4.dist-info/WHEEL
mloptimizer-0.9.4.dist-info/top_level.txt
mloptimizer-0.9.4.dist-info/RECORD
