Metadata-Version: 2.4
Name: mloptimizer
Version: 0.9.4
Summary: mloptimizer is a Python library for optimizing hyperparameters of machine learning algorithms using genetic algorithms.
Home-page: https://github.com/Caparrini/mloptimizer
Author: Antonio Caparrini López, Javier Arroyo Gallardo
Author-email: acaparri@ucm.es
Project-URL: Source, https://github.com/Caparrini/mloptimizer
Keywords: xgboost,genetic,deap
Classifier: Development Status :: 3 - Alpha
Classifier: Intended Audience :: Developers
Classifier: License :: OSI Approved :: MIT License
Classifier: Programming Language :: Python
Classifier: Programming Language :: Python :: 3
Classifier: Programming Language :: Python :: 3.9
Classifier: Programming Language :: Python :: 3.10
Classifier: Programming Language :: Python :: 3.11
Classifier: Programming Language :: Python :: 3.12
Classifier: Programming Language :: Python :: 3.13
Classifier: Operating System :: OS Independent
Requires-Python: >=3.9, <3.14
License-File: LICENSE
Requires-Dist: catboost>=1.1.1
Requires-Dist: deap>=1.3.3
Requires-Dist: joblib>=1.2.0
Requires-Dist: kaleido==0.2.1
Requires-Dist: numpy
Requires-Dist: pandas>=1.5.3
Requires-Dist: plotly>=5.15.0
Requires-Dist: matplotlib<3.10.0
Requires-Dist: python-dateutil>=2.8.1
Requires-Dist: pytz>=2022.7.1
Requires-Dist: scikit-learn<=1.5.2,>=1.2.1
Requires-Dist: scipy>=1.10.0
Requires-Dist: seaborn==0.12.2
Requires-Dist: six>=1.15.0
Requires-Dist: tqdm
Requires-Dist: xgboost>=1.7.3
Provides-Extra: dev
Requires-Dist: catboost>=1.1.1; extra == "dev"
Requires-Dist: deap>=1.3.3; extra == "dev"
Requires-Dist: joblib>=1.2.0; extra == "dev"
Requires-Dist: kaleido==0.2.1; extra == "dev"
Requires-Dist: keras>=2.13.1rc0; extra == "dev"
Requires-Dist: mlflow; extra == "dev"
Requires-Dist: numpy; extra == "dev"
Requires-Dist: pandas>=1.5.3; extra == "dev"
Requires-Dist: plotly>=5.15.0; extra == "dev"
Requires-Dist: matplotlib<3.10.0; extra == "dev"
Requires-Dist: pytest-cov; extra == "dev"
Requires-Dist: pytest-mock; extra == "dev"
Requires-Dist: python-dateutil>=2.8.1; extra == "dev"
Requires-Dist: pytz>=2022.7.1; extra == "dev"
Requires-Dist: scikit-learn<=1.5.2,>=1.2.1; extra == "dev"
Requires-Dist: scipy>=1.10.0; extra == "dev"
Requires-Dist: seaborn==0.12.2; extra == "dev"
Requires-Dist: six>=1.15.0; extra == "dev"
Requires-Dist: sphinx-autoapi; extra == "dev"
Requires-Dist: sphinx-favicon; extra == "dev"
Requires-Dist: sphinx-gallery==0.14.0; extra == "dev"
Requires-Dist: pydata-sphinx-theme; extra == "dev"
Requires-Dist: sphinx_mdinclude; extra == "dev"
Requires-Dist: sphinxcontrib-mermaid; extra == "dev"
Requires-Dist: tensorflow>=2.12.0; extra == "dev"
Requires-Dist: tqdm; extra == "dev"
Requires-Dist: xgboost>=1.7.3; extra == "dev"
Requires-Dist: hyperopt; extra == "dev"
Requires-Dist: ucimlrepo; extra == "dev"
Requires-Dist: sphinx-github-changelog; extra == "dev"
Requires-Dist: sphinx-contributors; extra == "dev"
Requires-Dist: sphinx_copybutton; extra == "dev"
Provides-Extra: docs
Requires-Dist: catboost>=1.1.1; extra == "docs"
Requires-Dist: deap>=1.3.3; extra == "docs"
Requires-Dist: hyperopt; extra == "docs"
Requires-Dist: joblib>=1.2.0; extra == "docs"
Requires-Dist: kaleido==0.2.1; extra == "docs"
Requires-Dist: keras>=2.13.1rc0; extra == "docs"
Requires-Dist: numpy; extra == "docs"
Requires-Dist: pandas>=1.5.3; extra == "docs"
Requires-Dist: plotly>=5.15.0; extra == "docs"
Requires-Dist: matplotlib<3.10.0; extra == "docs"
Requires-Dist: mlflow; extra == "docs"
Requires-Dist: pytest-cov; extra == "docs"
Requires-Dist: python-dateutil>=2.8.1; extra == "docs"
Requires-Dist: pytz>=2022.7.1; extra == "docs"
Requires-Dist: scikit-learn<=1.5.2,>=1.2.1; extra == "docs"
Requires-Dist: scipy>=1.10.0; extra == "docs"
Requires-Dist: seaborn==0.12.2; extra == "docs"
Requires-Dist: six>=1.15.0; extra == "docs"
Requires-Dist: sphinx-autoapi; extra == "docs"
Requires-Dist: sphinx-favicon; extra == "docs"
Requires-Dist: sphinx-gallery==0.14.0; extra == "docs"
Requires-Dist: pydata-sphinx-theme; extra == "docs"
Requires-Dist: sphinx_mdinclude; extra == "docs"
Requires-Dist: sphinxcontrib-mermaid; extra == "docs"
Requires-Dist: sphinx-autodoc-typehints; extra == "docs"
Requires-Dist: tensorflow>=2.12.0; extra == "docs"
Requires-Dist: tqdm; extra == "docs"
Requires-Dist: xgboost>=1.7.3; extra == "docs"
Requires-Dist: lightgbm; extra == "docs"
Requires-Dist: sphinx-github-changelog; extra == "docs"
Requires-Dist: sphinx-contributors; extra == "docs"
Requires-Dist: sphinx_copybutton; extra == "docs"
Dynamic: author
Dynamic: author-email
Dynamic: classifier
Dynamic: description
Dynamic: description-content-type
Dynamic: home-page
Dynamic: keywords
Dynamic: license-file
Dynamic: project-url
Dynamic: provides-extra
Dynamic: requires-dist
Dynamic: requires-python
Dynamic: summary
